virtualenvwrapper/anchorer/_version.py
virtualenvwrapper/anchorer/fix.py
virtualenvwrapper/anchorer/plugin.py
anchorer-0.4.0.dist-info/METADATA
anchorer-0.4.0.dist-info/WHEEL
anchorer-0.4.0.dist-info/entry_points.txt
anchorer-0.4.0.dist-info/top_level.txt
anchorer-0.4.0.dist-info/zip-safe
anchorer-0.4.0.dist-info/RECORD
