Metadata-Version: 2.1
Name: anchorer
Version: 0.4.0
Summary: Avoid breakages that would occur from updating symlinks to running virtualenvs
Author-email: Oliver Bristow <oliver+github@oliverbristow.co.uk>
Project-URL: homepage, https://github.com/Code0x58/anchorer
Project-URL: repository, https://github.com/Code0x58/anchorer
Keywords: virtualenv,virtualenvwrapper,symlink,resolve,deployment
Classifier: Development Status :: 4 - Beta
Classifier: Environment :: Plugins
Classifier: Intended Audience :: System Administrators
Classifier: Natural Language :: English
Classifier: Operating System :: OS Independent
Requires-Python: >3.3
Requires-Dist: virtualenvwrapper
